utme/__init__.py
utme/_alphabet.py
utme/_input.py
utme/_machine.py
utme/_output.py
utme/_rules.py
utme/_runner.py
utme/_state.py
utme/_symbol.py
utme/_tape.py
utme-1.0.1.dist-info/licenses/LICENSE
utme-1.0.1.dist-info/WHEEL
utme-1.0.1.dist-info/METADATA
utme-1.0.1.dist-info/RECORD
