Metadata-Version: 2.4
Name: utme
Version: 1.0.1
Summary: Universal Turing Machine Emulator.
Keywords: turing,machine,emulator
Author-email: Karam Assany <karam.assany@disroot.org>
Requires-Python: >=3.12
Classifier: Development Status :: 5 - Production/Stable
Classifier: Intended Audience :: Developers
Classifier: Intended Audience :: Education
Classifier: Intended Audience :: Science/Research
Classifier: License :: OSI Approved :: MIT License
Classifier: Natural Language :: English
Classifier: Operating System :: OS Independent
Classifier: Programming Language :: Python :: 3.12
Classifier: Programming Language :: Python :: 3.13
Classifier: Programming Language :: Python :: 3.14
Classifier: Topic :: Scientific/Engineering :: Mathematics
Classifier: Topic :: Software Development :: Interpreters
Classifier: Topic :: System :: Emulators
Classifier: Typing :: Typed
License-File: LICENSE
Project-URL: repository, https://codeberg.org/karam/utme
